{"expireTime":9007200878804910000,"key":"a624b4401bf649a742a79a760420668d","val":{"name":"IMAGE_PROCESSING","inputPaths":["/Volumes/macOS Data/projects/creador/.cache/caches/gatsby-source-wordpress-experimental/a8dc265bdde2a17e1b4098f350966532/imagee-01.png"],"outputDir":"/Volumes/macOS Data/projects/creador/public/static/c5cc7656ed6f29a06c8da3512da9f0ec","args":{"isLazy":false,"operations":[{"outputPath":"ae783/imagee-01.png","args":{"width":157,"toFormat":"png","quality":90}},{"outputPath":"679a3/imagee-01.png","args":{"width":315,"toFormat":"png","quality":90}}],"pluginOptions":{"base64Width":20,"forceBase64Format":"","useMozJpeg":false,"stripMetadata":true,"lazyImageGeneration":true,"defaultQuality":50,"failOnError":true,"plugins":[]}}}}