{"expireTime":9007200878900737000,"key":"e41759710c80deb0196435253f9e3c3f","val":{"name":"IMAGE_PROCESSING","inputPaths":["/Volumes/macOS Data/projects/creador/.cache/caches/gatsby-source-wordpress-experimental/a9c06e5ad9fabc1af4c772b6071d36a7/type-script.png"],"outputDir":"/Volumes/macOS Data/projects/creador/public/static/58b3a4c5e3a223071a35f25fa4b257fb","args":{"isLazy":false,"operations":[{"outputPath":"43fa5/type-script.png","args":{"width":250,"toFormat":"png","quality":90}},{"outputPath":"c6e3d/type-script.png","args":{"width":500,"toFormat":"png","quality":90}},{"outputPath":"da8b6/type-script.png","args":{"width":1000,"toFormat":"png","quality":90}}],"pluginOptions":{"base64Width":20,"forceBase64Format":"","useMozJpeg":false,"stripMetadata":true,"lazyImageGeneration":true,"defaultQuality":50,"failOnError":true,"plugins":[]}}}}