{"expireTime":9007200878804855000,"key":"d9fd166472f782ed636367fc0f195457","val":{"name":"IMAGE_PROCESSING","inputPaths":["/Volumes/macOS Data/projects/creador/.cache/caches/gatsby-source-wordpress-experimental/5ae8e0118561c1646753c09fb443aa40/Xiaomi-Redmi-Note-8T-16.jpg"],"outputDir":"/Volumes/macOS Data/projects/creador/public/static/03e50559ae6df69aa7903e79d7dace0d","args":{"isLazy":false,"operations":[{"outputPath":"16d62/Xiaomi-Redmi-Note-8T-16.jpg","args":{"width":200,"toFormat":"jpg","quality":90}},{"outputPath":"27ec1/Xiaomi-Redmi-Note-8T-16.jpg","args":{"width":400,"toFormat":"jpg","quality":90}},{"outputPath":"5fd6b/Xiaomi-Redmi-Note-8T-16.jpg","args":{"width":800,"toFormat":"jpg","quality":90}}],"pluginOptions":{"base64Width":20,"forceBase64Format":"","useMozJpeg":false,"stripMetadata":true,"lazyImageGeneration":true,"defaultQuality":50,"failOnError":true,"plugins":[]}}}}