{"expireTime":9007200878900740000,"key":"54311f4a74acbfc2d58a4f4e594c3d4e","val":{"name":"IMAGE_PROCESSING","inputPaths":["/Volumes/macOS Data/projects/creador/.cache/caches/gatsby-source-wordpress-experimental/fafd4e3685a3d335a32a87ece18732f0/react-fragments.png"],"outputDir":"/Volumes/macOS Data/projects/creador/public/static/53f8fa21652e0e94700fc7c7f0b1680c","args":{"isLazy":false,"operations":[{"outputPath":"85b06/react-fragments.png","args":{"width":256,"toFormat":"png","quality":90}},{"outputPath":"bc282/react-fragments.png","args":{"width":512,"toFormat":"png","quality":90}},{"outputPath":"f1720/react-fragments.png","args":{"width":1024,"toFormat":"png","quality":90}},{"outputPath":"4af54/react-fragments.png","args":{"width":1400,"toFormat":"png","quality":90}}],"pluginOptions":{"base64Width":20,"forceBase64Format":"","useMozJpeg":false,"stripMetadata":true,"lazyImageGeneration":true,"defaultQuality":50,"failOnError":true,"plugins":[]}}}}